{
    "type": "FeatureCollection",
    "name": "Fire_Hydrants",
    "crs": { "type": "name", "properties": { "name": "urn:ogc:def:crs:OGC:1.3:CRS84" } },
    "features": [
        { "type": "Feature", "properties": { "Category": "bar" }, "geometry": { "type": "Point", "coordinates": [ -77.010603579689104, 38.817203247241792 ] } },
        { "type": "Feature", "properties": { "Category": "bar" }, "geometry": { "type": "Point", "coordinates": [ -76.941676946088975, 38.91060100396907 ] } },
        { "type": "Feature", "properties": { "Category": "bar" }, "geometry": { "type": "Point", "coordinates": [ -76.988210780769222, 38.855230823908229 ] } },
        { "type": "Feature", "properties": { "Category": "bar" }, "geometry": { "type": "Point", "coordinates": [ -77.007372231866, 38.836398223772086 ] } },
        { "type": "Feature", "properties": { "Category": "bar" }, "geometry": { "type": "Point", "coordinates": [ -76.986730624517008, 38.86521189799749 ] } },
        { "type": "Feature", "properties": { "Category": "bar" }, "geometry": { "type": "Point", "coordinates": [ -77.020319390465332, 38.922661942425727 ] } },
        { "type": "Feature", "properties": { "Category": "bar" }, "geometry": { "type": "Point", "coordinates": [ -77.019573310511049, 38.92273402826811 ] } },
        { "type": "Feature", "properties": { "Category": "coffee" }, "geometry": { "type": "Point", "coordinates": [ -76.986210125507668, 38.863309512408904 ] } },
        { "type": "Feature", "properties": { "Category": "bar" }, "geometry": { "type": "Point", "coordinates": [ -77.068673187528276, 38.94497455503442 ] } },
        { "type": "Feature", "properties": { "Category": "bar" }, "geometry": { "type": "Point", "coordinates": [ -76.984785055366245, 38.864858026382549 ] } },
        { "type": "Feature", "properties": { "Category": "bar" }, "geometry": { "type": "Point", "coordinates": [ -77.000502398066857, 38.83782231422726 ] } },
        { "type": "Feature", "properties": { "Category": "bar" }, "geometry": { "type": "Point", "coordinates": [ -77.085642473411596, 38.909663967958799 ] } },
        { "type": "Feature", "properties": { "Category": "bar" }, "geometry": { "type": "Point", "coordinates": [ -77.064778867834093, 38.942471194364742 ] } },
        { "type": "Feature", "properties": { "Category": "bar" }, "geometry": { "type": "Point", "coordinates": [ -77.000497569978577, 38.83424731674706 ] } },
        { "type": "Feature", "properties": { "Category": "bar" }, "geometry": { "type": "Point", "coordinates": [ -76.986617042506609, 38.85552272343125 ] } }
    ]
    }
